pjlink/__init__.py
pjlink/cli.py
pjlink/cliutils.py
pjlink/projector.py
pjlink/protocol.py
pjlink-1.1.dist-info/LICENSE
pjlink-1.1.dist-info/METADATA
pjlink-1.1.dist-info/WHEEL
pjlink-1.1.dist-info/entry_points.txt
pjlink-1.1.dist-info/top_level.txt
pjlink-1.1.dist-info/RECORD
