Metadata-Version: 2.1
Name: pjlink
Version: 1.1
Summary: PJLink is a standard for controlling data projectors.
Home-page: http://hg.flowblok.id.au/pjlink
Author: Peter Ward
Author-email: peteraward@gmail.com
License: UNKNOWN
Platform: UNKNOWN
Classifier: Development Status :: 5 - Production/Stable
Classifier: Environment :: Console
Classifier: License :: OSI Approved :: Apache Software License
Classifier: Natural Language :: English
Classifier: Topic :: Multimedia :: Video :: Display
Classifier: Topic :: Utilities
Requires-Dist: appdirs
Requires-Dist: six
